acdh_wikidata_pyutils/__init__.py
acdh_wikidata_pyutils-3.0.dist-info/WHEEL
acdh_wikidata_pyutils-3.0.dist-info/METADATA
acdh_wikidata_pyutils-3.0.dist-info/RECORD
