Metadata-Version: 2.3
Name: acdh-wikidata-pyutils
Version: 3.0
Summary: Python package to fetch data from Wikidata
Keywords: Wikidata,api client
Author: Peter Andorfer
Author-email: Peter Andorfer <peter.andorfer@oeaw.ac.at>
License: MIT License
Requires-Dist: acdh-arche-assets>=3.25.0
Requires-Dist: requests>=2.32.5
Requires-Dist: typing-extensions>=4.15.0
Requires-Dist: wikidata>=0.8.1
Requires-Python: >=3.10
Project-URL: Repository, https://github.com/acdh-oeaw/acdh-wikidata-pyutils
